SimplePsycho/PsychopyManager.py
SimplePsycho/__init__.py
SimplePsycho/configManager.py
SimpleTasks/PsychopyTasks.py
SimpleTasks/__init__.py
SimplePsycho-1.0.dist-info/LICENSE
SimplePsycho-1.0.dist-info/METADATA
SimplePsycho-1.0.dist-info/WHEEL
SimplePsycho-1.0.dist-info/top_level.txt
SimplePsycho-1.0.dist-info/RECORD
